hidateinfer/__init__.py
hidateinfer/date_elements.py
hidateinfer/infer.py
hidateinfer/meta.yaml
hidateinfer/ruleproc.py
hidateinfer/tests/examples.yaml
hidateinfer/tests/test_infer.py
hi_dateinfer-0.4.6.dist-info/LICENSE
hi_dateinfer-0.4.6.dist-info/METADATA
hi_dateinfer-0.4.6.dist-info/WHEEL
hi_dateinfer-0.4.6.dist-info/top_level.txt
hi_dateinfer-0.4.6.dist-info/RECORD
