Metadata-Version: 2.1
Name: hi-dateinfer
Version: 0.4.6
Summary: Infers date format from examples, by using a series of pattern matching and rewriting rules to compute a 'best guess' datetime.strptime format string give a list of example date strings.
Home-page: https://github.com/hi-primus/hi-dateinfer
Author: Jeffrey Starr
Author-email: will@pedalwrencher.com
License: Apache Software License 2.0
Keywords: dateinfer
Platform: UNKNOWN
Classifier: Development Status :: 4 - Beta
Classifier: Intended Audience :: Developers
Classifier: License :: OSI Approved :: Apache Software License
Classifier: Operating System :: OS Independent
Classifier: Programming Language :: Python
Classifier: Programming Language :: Python :: 3
Classifier: Topic :: Software Development :: Libraries :: Python Modules
Requires-Python: !=3.0.*, !=3.1.*, !=3.2.*, !=3.3.*, !=3.4.*
License-File: LICENSE
Requires-Dist: wheel
Requires-Dist: pytz
